QPrimaryFlightDisplay.py
QPrimaryFlightDisplay-1.0.0a2.dist-info/LICENSE
QPrimaryFlightDisplay-1.0.0a2.dist-info/METADATA
QPrimaryFlightDisplay-1.0.0a2.dist-info/WHEEL
QPrimaryFlightDisplay-1.0.0a2.dist-info/top_level.txt
QPrimaryFlightDisplay-1.0.0a2.dist-info/RECORD
