Metadata-Version: 2.1
Name: QPrimaryFlightDisplay
Version: 1.0.0a2
Summary: T-standard compliant primary flight display widget for showing realtime flight data
Author: Tolga Demirdal
License: GNU GENERAL PUBLIC LICENSE
Project-URL: Homepage, https://github.com/shadymeowy/QPrimaryFlightDisplay
Project-URL: Repository, https://github.com/shadymeowy/QPrimaryFlightDisplay
License-File: LICENSE
Requires-Dist: PySide6
